Quelert/Quelert.py
Quelert/Stopwatch_en.py
Quelert/Stopwatch_ru.py
Quelert/__init__.py
Python_Quelert-1.0.6.dist-info/METADATA
Python_Quelert-1.0.6.dist-info/WHEEL
Python_Quelert-1.0.6.dist-info/top_level.txt
Python_Quelert-1.0.6.dist-info/RECORD
