Metadata-Version: 2.1
Name: Python-Quelert
Version: 1.0.6
Summary: Quelert V1Q6p311
Author: Georgy2008
Author-email: zadvornow2908@gmail.com
Classifier: Programming Language :: Python :: 3
Classifier: License :: OSI Approved :: MIT License
Classifier: Operating System :: OS Independent
Requires-Python: >=3.6
